jules_api/__init__.py
jules_api/client.py
jules_api/models.py
jules_api-1.0.1.dist-info/METADATA
jules_api-1.0.1.dist-info/WHEEL
jules_api-1.0.1.dist-info/top_level.txt
jules_api-1.0.1.dist-info/RECORD
